LICENSE
MANIFEST.in
README.rst
setup.py
django_switter.egg-info/PKG-INFO
django_switter.egg-info/SOURCES.txt
django_switter.egg-info/dependency_links.txt
django_switter.egg-info/not-zip-safe
django_switter.egg-info/requires.txt
django_switter.egg-info/top_level.txt
switter/__init__.py
switter/models.py
switter/settings.py
switter/tweets.py
switter/urls.py
switter/views.py
switter/migrations/0001_initial.py
switter/migrations/__init__.py
switter/plugins/__init__.py
switter/plugins/cms_plugins.py
switter/plugins/models.py
switter/plugins/settings.py
switter/plugins/migrations/0001_initial.py
switter/plugins/migrations/__init__.py
switter/plugins/templates/cms/plugins/switter/default.html
switter/static/js/jquery.switter.js