Metadata-Version: 1.1
Name: django-switter
Version: 0.1
Summary: Switter is a drop-in Django app that gets tweets for you, keeps them cached for a short while and makes it easy to display them on your site. Switter provides a django-cms plugin.
Home-page: https://bitbucket.org/grucha/django-switter
Author: Sylwester Gruszka
Author-email: gruszex@gmail.com
License: MIT
Platform: UNKNOWN
Classifier: Development Status :: 3 - Alpha
Classifier: Environment :: Web Environment
Classifier: Intended Audience :: Developers
Classifier: License :: OSI Approved :: MIT License
Classifier: Operating System :: OS Independent
Classifier: Programming Language :: Python
Classifier: Framework :: Django
